pyriskadjust/__init__.py
pyriskadjust/pyriskadjust.py
pyriskadjust/coefficients/__init__.py
pyriskadjust/coefficients/coefficients_2018_v21.py
pyriskadjust/coefficients/coefficients_2018_v22.py
pyriskadjust/coefficients/coefficients_2019_v23.py
pyriskadjust/hccs/__init__.py
pyriskadjust/hccs/hccs_v20.py
pyriskadjust/hccs/hccs_v22.py
pyriskadjust/hccs/hccs_v23.py
pyriskadjust/hccs/hccs_v24.py
pyriskadjust/icd_mapping/__init__.py
pyriskadjust/icd_mapping/mapping_2018_v21.py
pyriskadjust/icd_mapping/mapping_2018_v22.py
pyriskadjust/icd_mapping/mapping_2019_v23.py
pyriskadjust/icd_mapping/mapping_2020_v24.py
pyriskadjust/icd_mapping/mapping_2021_v22.py
pyriskadjust/icd_mapping/mapping_2021_v24.py
pyriskadjust/models/__init__.py
pyriskadjust/models/common.py
pyriskadjust/models/model_2018_v22.py
pyriskadjust/models/model_2019_v23.py
pyriskadjust/utils/__init__.py
pyriskadjust/utils/graph.py
pyriskadjust/utils/hcc_to_mapping.py
pyriskadjust-0.9.6.dist-info/AUTHORS.rst
pyriskadjust-0.9.6.dist-info/LICENSE
pyriskadjust-0.9.6.dist-info/METADATA
pyriskadjust-0.9.6.dist-info/WHEEL
pyriskadjust-0.9.6.dist-info/top_level.txt
pyriskadjust-0.9.6.dist-info/RECORD
