Metadata-Version: 2.1
Name: pyriskadjust
Version: 0.9.6
Summary: A python implementation of CMS's Medicare Risk Adjustment model based on Hierarchical Condition Categories (HCCs)
Home-page: https://github.com/calyxhealth/pyriskadjust
Author: Kevin Matulef
Author-email: kevin@calyxhealth.com
License: MIT license
Keywords: pyriskadjust
Platform: UNKNOWN
Classifier: Development Status :: 2 - Pre-Alpha
Classifier: Intended Audience :: Developers
Classifier: License :: OSI Approved :: MIT License
Classifier: Natural Language :: English
Classifier: Programming Language :: Python :: 2
Classifier: Programming Language :: Python :: 2.7
Classifier: Programming Language :: Python :: 3
Classifier: Programming Language :: Python :: 3.4
Classifier: Programming Language :: Python :: 3.5
Classifier: Programming Language :: Python :: 3.6
Classifier: Programming Language :: Python :: 3.7
